MANIFEST.in
requirements.txt
setup.cfg
setup.py
test-requirements.txt
flume/__init__.py
flume/cli.py
flume/core.py
flume/logger.py
flume/moment.py
flume/point.py
flume.egg-info/PKG-INFO
flume.egg-info/SOURCES.txt
flume.egg-info/dependency_links.txt
flume.egg-info/entry_points.txt
flume.egg-info/requires.txt
flume.egg-info/top_level.txt
flume/adapters/__init__.py
flume/adapters/adapter.py
flume/adapters/http.py
flume/adapters/stdio.py
flume/adapters/elastic/__init__.py
flume/adapters/elastic/node.py
flume/adapters/elastic/query.py
flume/adapters/streamers/__init__.py
flume/adapters/streamers/base.py
flume/adapters/streamers/csver.py
flume/adapters/streamers/grok.py
flume/adapters/streamers/jsoner.py
flume/adapters/streamers/jsonler.py
flume/exceptions/__init__.py
flume/procs/__init__.py
flume/procs/diff.py
flume/procs/filter.py
flume/procs/head.py
flume/procs/intersect.py
flume/procs/keep.py
flume/procs/put.py
flume/procs/remove.py
flume/procs/reorder.py
flume/procs/seq.py
flume/procs/sort.py
flume/procs/tail.py
flume/procs/union.py
flume/procs/reduce/__init__.py
flume/procs/reduce/core.py
flume/procs/reduce/reducers/__init__.py
flume/procs/reduce/reducers/count.py
flume/procs/reduce/reducers/funcr.py
flume/procs/reduce/reducers/iterate.py
flume/procs/reduce/reducers/maximum.py
flume/procs/reduce/reducers/minimum.py
flume/procs/reduce/reducers/date/__init__.py
flume/procs/reduce/reducers/math/__init__.py
flume/sinks/__init__.py
flume/sinks/barchart.py
flume/sinks/linechart.py
flume/sinks/memory.py
flume/sinks/timechart.py
flume/sinks/write.py
flume/sinks/views/__init__.py
flume/sinks/views/base.py
flume/sinks/views/gnuplot.py
flume/sinks/views/pygalview.py
flume/sources/__init__.py
flume/sources/emit.py
flume/sources/read.py
flume/thirdparty/__init__.py
flume/thirdparty/syslog.py
flume/thirdparty/github/__init__.py
flume/thirdparty/github/issues.py
flume/thirdparty/github/pulls.py
flume/thirdparty/github/util.py
flume/util/__init__.py
flume/util/compat.py
flume/util/terminal.py
site/__init__.py
test/benchmark/__init__.py
test/benchmark/sources/__init__.py
test/benchmark/sources/test_emit.py
test/integration/__init__.py
